{
    "query_state": [
        -0.5953165888786316,
        1.0135117769241333,
        -0.13217057287693024,
        -1.1745842695236206,
        0.11890659481287003,
        2.0969319343566895,
        -0.13845153152942657,
        0.0
    ],
    "query_prompt": "",
    "inference_time": true,
    "retrieved_0_state": [
        -0.6177452802658081,
        0.8631003499031067,
        -0.07535510510206223,
        -1.537758469581604,
        0.21158258616924286,
        2.333611011505127,
        -0.2921960651874542,
        0.0
    ],
    "retrieved_0_actions": [
        [
            -0.08542928844690323,
            0.16692830249667168,
            -0.031838195864111185,
            0.4566323757171631,
            0.04312882665544748,
            -0.26200316846370697,
            0.02508841920644045,
            0.0
        ],
        [
            0.0,
            0.0,
            0.0,
            0.0,
            0.0,
            0.0,
            0.0,
            0.0
        ],
        [
            0.0,
            0.0,
            0.0,
            0.0,
            0.0,
            0.0,
            0.0,
            0.0
        ],
        [
            0.0,
            0.0,
            0.0,
            0.0,
            0.0,
            0.0,
            0.0,
            0.0
        ],
        [
            0.0,
            0.0,
            0.0,
            0.0,
            0.0,
            0.0,
            0.0,
            0.0
        ],
        [
            0.0,
            0.0,
            0.0,
            0.0,
            0.0,
            0.0,
            0.0,
            0.0
        ],
        [
            0.0,
            0.0,
            0.0,
            0.0,
            0.0,
            0.0,
            0.0,
            0.0
        ],
        [
            0.0,
            0.0,
            0.0,
            0.0,
            0.0,
            0.0,
            0.0,
            0.0
        ],
        [
            0.0,
            0.0,
            0.0,
            0.0,
            0.0,
            0.0,
            0.0,
            0.0
        ],
        [
            0.0,
            0.0,
            0.0,
            0.0,
            0.0,
            0.0,
            0.0,
            0.0
        ]
    ],
    "retrieved_0_prompt": "move the idli plate to the right",
    "final_image_shape": [
        672,
        448,
        3
    ]
}