{
    "query_state": [
        0.0847766175866127,
        0.845061719417572,
        -0.0762154683470726,
        -1.5968092679977417,
        -0.04295996204018593,
        2.2740018367767334,
        0.12819421291351318,
        0.0
    ],
    "query_prompt": "rnp",
    "inference_time": true,
    "retrieved_0_state": [
        0.19310477375984192,
        0.43550342321395874,
        0.013048386201262474,
        -2.238745927810669,
        -0.08167783915996552,
        2.5388147830963135,
        0.25706714391708374,
        0.0
    ],
    "retrieved_0_actions": [
        -0.01865851692855358,
        -0.00029632559744641185,
        0.0168161210604012,
        0.009151235572062433,
        -0.007797455182299018,
        -0.014642429305240512,
        0.0025082286447286606,
        0.0,
        0.0,
        0.0,
        0.0,
        0.0,
        0.0,
        0.0,
        0.0,
        0.0,
        0.0,
        0.0,
        0.0,
        0.0,
        0.0,
        0.0,
        0.0,
        0.0,
        0.0,
        0.0,
        0.0,
        0.0,
        0.0,
        0.0,
        0.0,
        0.0,
        0.0,
        0.0,
        0.0,
        0.0,
        0.0,
        0.0,
        0.0,
        0.0,
        0.0,
        0.0,
        0.0,
        0.0,
        0.0,
        0.0,
        0.0,
        0.0,
        0.0,
        0.0,
        0.0,
        0.0,
        0.0,
        0.0,
        0.0,
        0.0,
        0.0,
        0.0,
        0.0,
        0.0,
        0.0,
        0.0,
        0.0,
        0.0,
        0.0,
        0.0,
        0.0,
        0.0,
        0.0,
        0.0,
        0.0,
        0.0,
        0.0,
        0.0,
        0.0,
        0.0,
        0.0,
        0.0,
        0.0,
        0.0
    ],
    "retrieved_0_prompt": "move the idli plate forwards",
    "final_image_shape": [
        448,
        448,
        3
    ]
}