{
    "query_state": [
        0.1568610817193985,
        0.05255407094955444,
        0.22665192186832428,
        -2.3648250102996826,
        0.030772682279348373,
        2.1686854362487793,
        0.19197943806648254,
        0.0
    ],
    "query_prompt": "move the idli plate to the sink",
    "inference_time": true,
    "retrieved_0_state": [
        0.22213394939899445,
        0.10580223798751831,
        0.2205735743045807,
        -2.546776056289673,
        0.10138609260320663,
        2.6081795692443848,
        0.18692241609096527,
        0.0
    ],
    "retrieved_0_actions": [
        [
            0.17728954553604126,
            -0.10940761305391788,
            0.24192795157432556,
            -0.020889777224510908,
            0.37021685391664505,
            0.05240953993052244,
            0.004541901289485395,
            0.0
        ],
        [
            0.15225008130073547,
            -0.1251745130866766,
            0.21077336743474007,
            -0.00568315910641104,
            0.35653792321681976,
            0.026315187569707632,
            -0.020154621452093124,
            0.0
        ],
        [
            0.10987390764057636,
            -0.1854342594742775,
            0.15869604423642159,
            -0.002781977236736566,
            0.30502982437610626,
            -0.025565028190612793,
            -0.04906298592686653,
            0.0
        ],
        [
            0.0,
            0.0,
            0.0,
            0.0,
            0.0,
            0.0,
            0.0,
            0.0
        ],
        [
            0.0,
            0.0,
            0.0,
            0.0,
            0.0,
            0.0,
            0.0,
            0.0
        ],
        [
            0.0,
            0.0,
            0.0,
            0.0,
            0.0,
            0.0,
            0.0,
            0.0
        ],
        [
            0.0,
            0.0,
            0.0,
            0.0,
            0.0,
            0.0,
            0.0,
            0.0
        ],
        [
            0.0,
            0.0,
            0.0,
            0.0,
            0.0,
            0.0,
            0.0,
            0.0
        ],
        [
            0.0,
            0.0,
            0.0,
            0.0,
            0.0,
            0.0,
            0.0,
            0.0
        ],
        [
            0.0,
            0.0,
            0.0,
            0.0,
            0.0,
            0.0,
            0.0,
            0.0
        ],
        [
            0.0,
            0.0,
            0.0,
            0.0,
            0.0,
            0.0,
            0.0,
            0.0
        ],
        [
            0.0,
            0.0,
            0.0,
            0.0,
            0.0,
            0.0,
            0.0,
            0.0
        ],
        [
            0.0,
            0.0,
            0.0,
            0.0,
            0.0,
            0.0,
            0.0,
            0.0
        ],
        [
            0.0,
            0.0,
            0.0,
            0.0,
            0.0,
            0.0,
            0.0,
            0.0
        ],
        [
            0.0,
            0.0,
            0.0,
            0.0,
            0.0,
            0.0,
            0.0,
            0.0
        ]
    ],
    "retrieved_0_prompt": "move the idli plate to the sink",
    "retrieved_1_state": [
        0.24446681141853333,
        0.10329510271549225,
        0.24993328750133514,
        -2.5441107749938965,
        0.1355646401643753,
        2.611064910888672,
        0.18679708242416382,
        0.0
    ],
    "retrieved_1_actions": [
        [
            0.15225008130073547,
            -0.1251745130866766,
            0.21077336743474007,
            -0.00568315910641104,
            0.35653792321681976,
            0.026315187569707632,
            -0.020154621452093124,
            0.0
        ],
        [
            0.10987390764057636,
            -0.1854342594742775,
            0.15869604423642159,
            -0.002781977236736566,
            0.30502982437610626,
            -0.025565028190612793,
            -0.04906298592686653,
            0.0
        ],
        [
            0.0,
            0.0,
            0.0,
            0.0,
            0.0,
            0.0,
            0.0,
            0.0
        ],
        [
            0.0,
            0.0,
            0.0,
            0.0,
            0.0,
            0.0,
            0.0,
            0.0
        ],
        [
            0.0,
            0.0,
            0.0,
            0.0,
            0.0,
            0.0,
            0.0,
            0.0
        ],
        [
            0.0,
            0.0,
            0.0,
            0.0,
            0.0,
            0.0,
            0.0,
            0.0
        ],
        [
            0.0,
            0.0,
            0.0,
            0.0,
            0.0,
            0.0,
            0.0,
            0.0
        ],
        [
            0.0,
            0.0,
            0.0,
            0.0,
            0.0,
            0.0,
            0.0,
            0.0
        ],
        [
            0.0,
            0.0,
            0.0,
            0.0,
            0.0,
            0.0,
            0.0,
            0.0
        ],
        [
            0.0,
            0.0,
            0.0,
            0.0,
            0.0,
            0.0,
            0.0,
            0.0
        ],
        [
            0.0,
            0.0,
            0.0,
            0.0,
            0.0,
            0.0,
            0.0,
            0.0
        ],
        [
            0.0,
            0.0,
            0.0,
            0.0,
            0.0,
            0.0,
            0.0,
            0.0
        ],
        [
            0.0,
            0.0,
            0.0,
            0.0,
            0.0,
            0.0,
            0.0,
            0.0
        ],
        [
            0.0,
            0.0,
            0.0,
            0.0,
            0.0,
            0.0,
            0.0,
            0.0
        ],
        [
            0.0,
            0.0,
            0.0,
            0.0,
            0.0,
            0.0,
            0.0,
            0.0
        ]
    ],
    "retrieved_1_prompt": "move the idli plate to the sink",
    "retrieved_2_state": [
        0.2659001648426056,
        0.10096153616905212,
        0.27996015548706055,
        -2.5408973693847656,
        0.17261092364788055,
        2.6111929416656494,
        0.18648742139339447,
        0.0
    ],
    "retrieved_2_actions": [
        [
            0.10987390764057636,
            -0.1854342594742775,
            0.15869604423642159,
            -0.002781977236736566,
            0.30502982437610626,
            -0.025565028190612793,
            -0.04906298592686653,
            0.0
        ],
        [
            0.0,
            0.0,
            0.0,
            0.0,
            0.0,
            0.0,
            0.0,
            0.0
        ],
        [
            0.0,
            0.0,
            0.0,
            0.0,
            0.0,
            0.0,
            0.0,
            0.0
        ],
        [
            0.0,
            0.0,
            0.0,
            0.0,
            0.0,
            0.0,
            0.0,
            0.0
        ],
        [
            0.0,
            0.0,
            0.0,
            0.0,
            0.0,
            0.0,
            0.0,
            0.0
        ],
        [
            0.0,
            0.0,
            0.0,
            0.0,
            0.0,
            0.0,
            0.0,
            0.0
        ],
        [
            0.0,
            0.0,
            0.0,
            0.0,
            0.0,
            0.0,
            0.0,
            0.0
        ],
        [
            0.0,
            0.0,
            0.0,
            0.0,
            0.0,
            0.0,
            0.0,
            0.0
        ],
        [
            0.0,
            0.0,
            0.0,
            0.0,
            0.0,
            0.0,
            0.0,
            0.0
        ],
        [
            0.0,
            0.0,
            0.0,
            0.0,
            0.0,
            0.0,
            0.0,
            0.0
        ],
        [
            0.0,
            0.0,
            0.0,
            0.0,
            0.0,
            0.0,
            0.0,
            0.0
        ],
        [
            0.0,
            0.0,
            0.0,
            0.0,
            0.0,
            0.0,
            0.0,
            0.0
        ],
        [
            0.0,
            0.0,
            0.0,
            0.0,
            0.0,
            0.0,
            0.0,
            0.0
        ],
        [
            0.0,
            0.0,
            0.0,
            0.0,
            0.0,
            0.0,
            0.0,
            0.0
        ],
        [
            0.0,
            0.0,
            0.0,
            0.0,
            0.0,
            0.0,
            0.0,
            0.0
        ]
    ],
    "retrieved_2_prompt": "move the idli plate to the sink",
    "retrieved_3_state": [
        0.19801591336727142,
        0.03386812284588814,
        0.2018730491399765,
        -2.6601736545562744,
        0.14531566202640533,
        2.6493442058563232,
        0.2860043942928314,
        0.0
    ],
    "retrieved_3_actions": [
        [
            -0.06544340401887894,
            0.2948623336851597,
            -0.11307804845273495,
            0.33581990748643875,
            -0.15179909765720367,
            0.06536651402711868,
            0.14873621053993702,
            0.0
        ],
        [
            -0.04209523554891348,
            0.22294258698821068,
            -0.0901283323764801,
            0.2930714748799801,
            -0.11762198060750961,
            0.020700781606137753,
            0.1411442644894123,
            0.0
        ],
        [
            -0.033521330915391445,
            0.13347972184419632,
            -0.06668922957032919,
            0.234428308904171,
            -0.07854038849473,
            -0.03489795373752713,
            0.11893180198967457,
            0.0
        ],
        [
            0.0,
            0.0,
            0.0,
            0.0,
            0.0,
            0.0,
            0.0,
            0.0
        ],
        [
            0.0,
            0.0,
            0.0,
            0.0,
            0.0,
            0.0,
            0.0,
            0.0
        ],
        [
            0.0,
            0.0,
            0.0,
            0.0,
            0.0,
            0.0,
            0.0,
            0.0
        ],
        [
            0.0,
            0.0,
            0.0,
            0.0,
            0.0,
            0.0,
            0.0,
            0.0
        ],
        [
            0.0,
            0.0,
            0.0,
            0.0,
            0.0,
            0.0,
            0.0,
            0.0
        ],
        [
            0.0,
            0.0,
            0.0,
            0.0,
            0.0,
            0.0,
            0.0,
            0.0
        ],
        [
            0.0,
            0.0,
            0.0,
            0.0,
            0.0,
            0.0,
            0.0,
            0.0
        ],
        [
            0.0,
            0.0,
            0.0,
            0.0,
            0.0,
            0.0,
            0.0,
            0.0
        ],
        [
            0.0,
            0.0,
            0.0,
            0.0,
            0.0,
            0.0,
            0.0,
            0.0
        ],
        [
            0.0,
            0.0,
            0.0,
            0.0,
            0.0,
            0.0,
            0.0,
            0.0
        ],
        [
            0.0,
            0.0,
            0.0,
            0.0,
            0.0,
            0.0,
            0.0,
            0.0
        ],
        [
            0.0,
            0.0,
            0.0,
            0.0,
            0.0,
            0.0,
            0.0,
            0.0
        ]
    ],
    "retrieved_3_prompt": "move the idli plate to the sink",
    "exp_lamda_distances": [
        [
            1.0
        ],
        [
            0.11893538704278916
        ],
        [
            0.06505368107532651
        ],
        [
            0.04451510135650258
        ],
        [
            0.021080066870905908
        ]
    ],
    "final_image_shape": [
        672,
        1120,
        3
    ]
}