{
    "48768": "Put the rubber band on the cup",
    "50433": "Put a rubber band around the base of the cup",
    "50817": "Put the elastic on the cup",
    "54912": "Put the rubber band on the cup",
    "89603": "Wrap a rubber band on the bottom of the cup",
    "94208": "Put the rubber band on the cup",
    "4487": "Place the rubber band on the bottom of the brown cup",
    "70408": "Put the rubber band around the brown cup",
    "76300": "Put the rubber band on the jar.",
    "82062": "Put the rubber band around the brown cup",
    "4496": "Put the rubber band around the brown cup",
    "10771": "Put a rubber band around the base of the cup",
    "57492": "Put the rubber band on the cup",
    "67478": "Put the rubber band on the cup",
    "61466": "Put the rubber band around the brown cup",
    "20642": "Put the rubber band around the cup",
    "26790": "Put the rubber band around the jar.",
    "79398": "Put the rubber band around the brown cup",
    "84271": "Put the rubber band on the jar.",
    "2225": "Put the rubber band on the brown cup",
    "39735": "Put the rubber band around the base of the cup",
    "25275": "Put the rubber band around the base of the cup",
    "49088": "Put an elastic band on the cup",
    "51394": "Put the rubber band around the base of the cup",
    "79939": "Put the rubber band on the jar.",
    "5830": "Put a rubber band around the cup",
    "16457": "Place the elastic band over the cup",
    "49611": "Put the rubber band around the jar.",
    "81355": "Put the rubber band around the jar.",
    "95051": "Put the band over the bottom of the cup",
    "39888": "Wrap the band over the bottom of the brown coffee cup",
    "48594": "Put the rubber band on the cup",
    "25939": "Put a rubber band around the base of the cup",
    "93148": "Put a rubber band around the brown cup",
    "71009": "Put the rubber band around the brown cup",
    "5986": "Put the rubber band around the base of the cup",
    "84449": "Put a rubber band around the cup",
    "14825": "Put the rubber band on the cup",
    "42477": "Put the rubber band around the brown cup",
    "85617": "Put the rubber band on the cup",
    "754": "Place the elastic on the bottom of the brown cup",
    "1906": "Put a rubber band around the cup",
    "49011": "Put the rubber band around the base of the cup",
    "52211": "Put the rubber band around the base of the cup",
    "24054": "Put the rubber band around the brown cup",
    "90869": "Put a rubber band around the cup",
    "66553": "Put the rubber band around the cup",
    "31098": "Put a rubber band around the cup",
    "3710": "Put the rubber band around the base of the cup",
    "57215": "Put the rubber band around the cup"
}